{
  "routes": [
    {
      "method": "GET",
      "path": "/equations",
      "handler": "equation.find",
      "config": {
        "policies": []
      }
    },
    {
      "method": "GET",
      "path": "/equations/count",
      "handler": "equation.count",
      "config": {
        "policies": []
      }
    },
    {
      "method": "GET",
      "path": "/equations/:id",
      "handler": "equation.findOne",
      "config": {
        "policies": []
      }
    },
    {
      "method": "POST",
      "path": "/equations",
      "handler": "equation.create",
      "config": {
        "policies": []
      }
    },
    {
      "method": "PUT",
      "path": "/equations/:id",
      "handler": "equation.update",
      "config": {
        "policies": []
      }
    },
    {
      "method": "DELETE",
      "path": "/equations/:id",
      "handler": "equation.delete",
      "config": {
        "policies": []
      }
    }
  ]
}
